{
    "abl": {
        "014V6u9VubefjaPPl1QkTJ": 1
    },
    "about": {
        "014V6u9VubefjaPPl1QkTJ": 1
    },
    "accroupi": {
        "00X2yv2vrtritPt2CZnUTZ": 1
    },
    "accus": {
        "014V6u9VubefjaPPl1QkTJ": 1
    },
    "acr": {
        "00X2yv2vrtritPt2CZnUTZ": 2
    },
    "adieu": {
        "00X2yv2vrtritPt2CZnUTZ": 1
    },
    "advantag": {
        "014V6u9VubefjaPPl1QkTJ": 1
    },
    "advers": {
        "014V6u9VubefjaPPl1QkTJ": 1
    },
    "ah": {
        "00X2yv2vrtritPt2CZnUTZ": 6,
        "014V6u9VubefjaPPl1QkTJ": 1
    },
    "ai": {
        "014V6u9VubefjaPPl1QkTJ": 2
    },
    "al": {
        "01bWQ4TPGmsP6FS64nF4R9": 3
    },
    "alex": {
        "01auWCuHXubb8KPZ0IXF4S": 1
    },
    "algéri": {
        "00X2yv2vrtritPt2CZnUTZ": 1
    },
    "all": {
        "014J7jX1wSv0manSdRnveo": 6,
        "014V6u9VubefjaPPl1QkTJ": 3,
        "01bWQ4TPGmsP6FS64nF4R9": 6
    },
    "allang": {
        "01bWQ4TPGmsP6FS64nF4R9": 2
    },
    "alleg": {
        "014V6u9VubefjaPPl1QkTJ": 1
    },
    "allow": {
        "014V6u9VubefjaPPl1QkTJ": 1
    },
    "along": {
        "00YeYHw6zhoy1y7EPTgIkj": 2
    },
    "alsof": {
        "01bWQ4TPGmsP6FS64nF4R9": 1
    },
    "am": {
        "014V6u9VubefjaPPl1QkTJ": 16
    },
    "amaz": {
        "014V6u9VubefjaPPl1QkTJ": 1
    },
    "ami": {
        "00X2yv2vrtritPt2CZnUTZ": 1
    },
    "an": {
        "014V6u9VubefjaPPl1QkTJ": 2
    },
    "and": {
        "00YeYHw6zhoy1y7EPTgIkj": 5,
        "00Z0GIRi0l7WqQnQJCo5S2": 12,
        "012mGdSYIBEmERuScm2iOl": 6,
        "014J7jX1wSv0manSdRnveo": 15,
        "014V6u9VubefjaPPl1QkTJ": 13,
        "01Bw3xiZ5PQfn0btMWICaQ": 6,
        "01bWQ4TPGmsP6FS64nF4R9": 3
    },
    "ani": {
        "014V6u9VubefjaPPl1QkTJ": 1
    },
    "anywher": {
        "01Bw3xiZ5PQfn0btMWICaQ": 3
    },
    "apart": {
        "00Z0GIRi0l7WqQnQJCo5S2": 6
    },
    "appli": {
        "014V6u9VubefjaPPl1QkTJ": 1
    },
    "are": {
        "014V6u9VubefjaPPl1QkTJ": 1,
        "01Bw3xiZ5PQfn0btMWICaQ": 2
    },
    "arm": {
        "00X2yv2vrtritPt2CZnUTZ": 2
    },
    "around": {
        "00YeYHw6zhoy1y7EPTgIkj": 1,
        "011gUcrvLDn2gEApOdOhVe": 1,
        "014J7jX1wSv0manSdRnveo": 2,
        "014V6u9VubefjaPPl1QkTJ": 1
    },
    "as": {
        "00WIXhVVhswHuS6dlkScuw": 4,
        "014V6u9VubefjaPPl1QkTJ": 4
    },
    "asap": {
        "014V6u9VubefjaPPl1QkTJ": 1
    },
    "asleep": {
        "00YeYHw6zhoy1y7EPTgIkj": 1
    },
    "ass": {
        "014V6u9VubefjaPPl1QkTJ": 1
    },
    "at": {
        "00WIXhVVhswHuS6dlkScuw": 16,
        "014J7jX1wSv0manSdRnveo": 1,
        "014V6u9VubefjaPPl1QkTJ": 4
    },
    "attaqu": {
        "00X2yv2vrtritPt2CZnUTZ": 1
    },
    "au": {
        "00X2yv2vrtritPt2CZnUTZ": 2
    },
    "avec": {
        "00X2yv2vrtritPt2CZnUTZ": 2
    },
    "awak": {
        "012mGdSYIBEmERuScm2iOl": 1
    },
    "away": {
        "00YeYHw6zhoy1y7EPTgIkj": 1,
        "014J7jX1wSv0manSdRnveo": 2
    },
    "b": {
        "00X2yv2vrtritPt2CZnUTZ": 1,
        "012mGdSYIBEmERuScm2iOl": 1,
        "014V6u9VubefjaPPl1QkTJ": 1
    },
    "babi": {
        "00WIXhVVhswHuS6dlkScuw": 18
    },
    "back": {
        "00YeYHw6zhoy1y7EPTgIkj": 1,
        "00Z0GIRi0l7WqQnQJCo5S2": 1,
        "014V6u9VubefjaPPl1QkTJ": 3
    },
    "bad": {
        "012mGdSYIBEmERuScm2iOl": 1
    },
    "baddest": {
        "00WIXhVVhswHuS6dlkScuw": 4
    },
    "baggio": {
        "00X2yv2vrtritPt2CZnUTZ": 1
    },
    "baiser": {
        "00X2yv2vrtritPt2CZnUTZ": 1
    },
    "balad": {
        "00X2yv2vrtritPt2CZnUTZ": 1
    },
    "ball": {
        "00X2yv2vrtritPt2CZnUTZ": 4,
        "014V6u9VubefjaPPl1QkTJ": 1
    },
    "ballon": {
        "00X2yv2vrtritPt2CZnUTZ": 1
    },
    "barbecu": {
        "014V6u9VubefjaPPl1QkTJ": 1
    },
    "bare": {
        "014V6u9VubefjaPPl1QkTJ": 1
    },
    "batistuta": {
        "00X2yv2vrtritPt2CZnUTZ": 1
    },
    "be": {
        "00WIXhVVhswHuS6dlkScuw": 2,
        "00YeYHw6zhoy1y7EPTgIkj": 2,
        "00Z0GIRi0l7WqQnQJCo5S2": 1,
        "012mGdSYIBEmERuScm2iOl": 2,
        "014V6u9VubefjaPPl1QkTJ": 9
    },
    "beauti": {
        "01Bw3xiZ5PQfn0btMWICaQ": 14
    },
    "beauté": {
        "00X2yv2vrtritPt2CZnUTZ": 1
    },
    "beaux": {
        "00X2yv2vrtritPt2CZnUTZ": 1
    },
    "bebeto": {
        "00X2yv2vrtritPt2CZnUTZ": 1
    },
    "bed": {
        "00WIXhVVhswHuS6dlkScuw": 2,
        "00Z0GIRi0l7WqQnQJCo5S2": 1
    },
    "been": {
        "00WIXhVVhswHuS6dlkScuw": 8,
        "011gUcrvLDn2gEApOdOhVe": 4,
        "012mGdSYIBEmERuScm2iOl": 1
    },
    "befor": {
        "014V6u9VubefjaPPl1QkTJ": 1
    },
    "belief": {
        "014V6u9VubefjaPPl1QkTJ": 1
    },
    "ben": {
        "01bWQ4TPGmsP6FS64nF4R9": 5
    },
    "benjamin": {
        "00YeYHw6zhoy1y7EPTgIkj": 1
    },
    "bent": {
        "01bWQ4TPGmsP6FS64nF4R9": 13
    },
    "bené": {
        "00X2yv2vrtritPt2CZnUTZ": 49
    },
    "benébelek": {
        "00X2yv2vrtritPt2CZnUTZ": 2
    },
    "benéchico": {
        "00X2yv2vrtritPt2CZnUTZ": 2
    },
    "best": {
        "014V6u9VubefjaPPl1QkTJ": 1
    },
    "bet": {
        "014J7jX1wSv0manSdRnveo": 1,
        "014V6u9VubefjaPPl1QkTJ": 1
    },
    "better": {
        "00Z0GIRi0l7WqQnQJCo5S2": 8,
        "012mGdSYIBEmERuScm2iOl": 6,
        "014J7jX1wSv0manSdRnveo": 1
    },
    "beyond": {
        "014V6u9VubefjaPPl1QkTJ": 1
    },
    "bicrav": {
        "00X2yv2vrtritPt2CZnUTZ": 1
    },
    "big": {
        "00YeYHw6zhoy1y7EPTgIkj": 1,
        "014J7jX1wSv0manSdRnveo": 1,
        "014V6u9VubefjaPPl1QkTJ": 1
    },
    "bij": {
        "01bWQ4TPGmsP6FS64nF4R9": 6
    },
    "billet": {
        "00X2yv2vrtritPt2CZnUTZ": 1
    },
    "bizzey": {
        "01bWQ4TPGmsP6FS64nF4R9": 1
    },
    "black": {
        "014J7jX1wSv0manSdRnveo": 1
    },
    "blood": {
        "014V6u9VubefjaPPl1QkTJ": 4
    },
    "blue": {
        "00YeYHw6zhoy1y7EPTgIkj": 1
    },
    "boat": {
        "012mGdSYIBEmERuScm2iOl": 1
    },
    "bodi": {
        "00WIXhVVhswHuS6dlkScuw": 8,
        "01bWQ4TPGmsP6FS64nF4R9": 9
    },
    "bold": {
        "014V6u9VubefjaPPl1QkTJ": 1
    },
    "bomb": {
        "014V6u9VubefjaPPl1QkTJ": 1
    },
    "boot": {
        "00YeYHw6zhoy1y7EPTgIkj": 1
    },
    "born": {
        "014V6u9VubefjaPPl1QkTJ": 4
    },
    "bottl": {
        "014J7jX1wSv0manSdRnveo": 1
    },
    "bottom": {
        "01Bw3xiZ5PQfn0btMWICaQ": 2
    },
    "bouquet": {
        "00X2yv2vrtritPt2CZnUTZ": 1
    },
    "box": {
        "00Z0GIRi0l7WqQnQJCo5S2": 1
    },
    "brain": {
        "014V6u9VubefjaPPl1QkTJ": 1
    },
    "break": {
        "00WIXhVVhswHuS6dlkScuw": 2,
        "00Z0GIRi0l7WqQnQJCo5S2": 20
    },
    "breath": {
        "014V6u9VubefjaPPl1QkTJ": 5
    },
    "broeder": {
        "01bWQ4TPGmsP6FS64nF4R9": 1
    },
    "broederliefd": {
        "01bWQ4TPGmsP6FS64nF4R9": 1
    },
    "broken": {
        "014J7jX1wSv0manSdRnveo": 1
    },
    "brésilienn": {
        "00X2yv2vrtritPt2CZnUTZ": 4
    },
    "bubbl": {
        "014V6u9VubefjaPPl1QkTJ": 1
    },
    "built": {
        "014V6u9VubefjaPPl1QkTJ": 1
    },
    "but": {
        "00Z0GIRi0l7WqQnQJCo5S2": 3,
        "014J7jX1wSv0manSdRnveo": 10,
        "014V6u9VubefjaPPl1QkTJ": 10
    },
    "butt": {
        "014V6u9VubefjaPPl1QkTJ": 1
    },
    "buurt": {
        "01bWQ4TPGmsP6FS64nF4R9": 6
    },
    "by": {
        "00YeYHw6zhoy1y7EPTgIkj": 2,
        "00Z0GIRi0l7WqQnQJCo5S2": 3,
        "014V6u9VubefjaPPl1QkTJ": 1
    },
    "ca": {
        "00Z0GIRi0l7WqQnQJCo5S2": 3,
        "014J7jX1wSv0manSdRnveo": 3,
        "014V6u9VubefjaPPl1QkTJ": 1
    },
    "cage": {
        "014V6u9VubefjaPPl1QkTJ": 1
    },
    "cake": {
        "00WIXhVVhswHuS6dlkScuw": 2
    },
    "calimero": {
        "00X2yv2vrtritPt2CZnUTZ": 1
    },
    "calum": {
        "014J7jX1wSv0manSdRnveo": 1
    },
    "came": {
        "014J7jX1wSv0manSdRnveo": 1
    },
    "can": {
        "00YeYHw6zhoy1y7EPTgIkj": 3,
        "011gUcrvLDn2gEApOdOhVe": 1,
        "014J7jX1wSv0manSdRnveo": 1,
        "014V6u9VubefjaPPl1QkTJ": 4,
        "01bWQ4TPGmsP6FS64nF4R9": 6
    },
    "capabl": {
        "014V6u9VubefjaPPl1QkTJ": 2
    },
    "car": {
        "00X2yv2vrtritPt2CZnUTZ": 1,
        "012mGdSYIBEmERuScm2iOl": 1
    },
    "caramelo": {
        "00X2yv2vrtritPt2CZnUTZ": 1
    },
    "caus": {
        "014V6u9VubefjaPPl1QkTJ": 9
    },
    "ce": {
        "00X2yv2vrtritPt2CZnUTZ": 1
    },
    "cent": {
        "00X2yv2vrtritPt2CZnUTZ": 2
    },
    "ces": {
        "00X2yv2vrtritPt2CZnUTZ": 1
    },
    "challeng": {
        "014V6u9VubefjaPPl1QkTJ": 1
    },
    "charcoal": {
        "014V6u9VubefjaPPl1QkTJ": 1
    },
    "check": {
        "012mGdSYIBEmERuScm2iOl": 1
    },
    "chica": {
        "00X2yv2vrtritPt2CZnUTZ": 1
    },
    "chico": {
        "00X2yv2vrtritPt2CZnUTZ": 6
    },
    "chier": {
        "00X2yv2vrtritPt2CZnUTZ": 1
    },
    "chillout": {
        "00YeYHw6zhoy1y7EPTgIkj": 1,
        "011gUcrvLDn2gEApOdOhVe": 1
    },
    "chixtap": {
        "00X2yv2vrtritPt2CZnUTZ": 1
    },
    "choos": {
        "011gUcrvLDn2gEApOdOhVe": 1
    },
    "christma": {
        "012mGdSYIBEmERuScm2iOl": 2
    },
    "christoph": {
        "014V6u9VubefjaPPl1QkTJ": 1
    },
    "circl": {
        "014J7jX1wSv0manSdRnveo": 1
    },
    "ck": {
        "00X2yv2vrtritPt2CZnUTZ": 1
    },
    "claus": {
        "012mGdSYIBEmERuScm2iOl": 21
    },
    "climb": {
        "014V6u9VubefjaPPl1QkTJ": 1
    },
    "clope": {
        "00X2yv2vrtritPt2CZnUTZ": 1
    },
    "cloth": {
        "00YeYHw6zhoy1y7EPTgIkj": 1
    },
    "clown": {
        "014V6u9VubefjaPPl1QkTJ": 1
    },
    "cock": {
        "014V6u9VubefjaPPl1QkTJ": 1
    },
    "code": {
        "00WIXhVVhswHuS6dlkScuw": 2
    },
    "coffr": {
        "00X2yv2vrtritPt2CZnUTZ": 1
    },
    "come": {
        "00YeYHw6zhoy1y7EPTgIkj": 1,
        "00Z0GIRi0l7WqQnQJCo5S2": 2,
        "012mGdSYIBEmERuScm2iOl": 1,
        "014J7jX1wSv0manSdRnveo": 2,
        "014V6u9VubefjaPPl1QkTJ": 1,
        "01bWQ4TPGmsP6FS64nF4R9": 3
    },
    "comin": {
        "012mGdSYIBEmERuScm2iOl": 20
    },
    "comm": {
        "00X2yv2vrtritPt2CZnUTZ": 1
    },
    "comment": {
        "00X2yv2vrtritPt2CZnUTZ": 2
    },
    "condamné": {
        "00X2yv2vrtritPt2CZnUTZ": 1
    },
    "confetti": {
        "00WIXhVVhswHuS6dlkScuw": 1
    },
    "control": {
        "00WIXhVVhswHuS6dlkScuw": 4
    },
    "convert": {
        "014V6u9VubefjaPPl1QkTJ": 1
    },
    "coo": {
        "012mGdSYIBEmERuScm2iOl": 1
    },
    "copin": {
        "00X2yv2vrtritPt2CZnUTZ": 1
    },
    "corner": {
        "014J7jX1wSv0manSdRnveo": 4
    },
    "corsica": {
        "00X2yv2vrtritPt2CZnUTZ": 1
    },
    "cost": {
        "014V6u9VubefjaPPl1QkTJ": 1
    },
    "couill": {
        "00X2yv2vrtritPt2CZnUTZ": 1
    },
    "could": {
        "00YeYHw6zhoy1y7EPTgIkj": 9,
        "011gUcrvLDn2gEApOdOhVe": 5
    },
    "cri": {
        "012mGdSYIBEmERuScm2iOl": 2
    },
    "crier": {
        "00X2yv2vrtritPt2CZnUTZ": 1
    },
    "cross": {
        "011gUcrvLDn2gEApOdOhVe": 1
    },
    "crypto": {
        "00WIXhVVhswHuS6dlkScuw": 2
    },
    "custom": {
        "00WIXhVVhswHuS6dlkScuw": 2
    },
    "cut": {
        "014V6u9VubefjaPPl1QkTJ": 1
    },
    "cypher": {
        "014V6u9VubefjaPPl1QkTJ": 1
    },
    "cypress": {
        "014V6u9VubefjaPPl1QkTJ": 1
    },
    "daar": {
        "01bWQ4TPGmsP6FS64nF4R9": 2
    },
    "dan": {
        "00X2yv2vrtritPt2CZnUTZ": 7,
        "01bWQ4TPGmsP6FS64nF4R9": 2
    },
    "danc": {
        "014J7jX1wSv0manSdRnveo": 7
    },
    "dat": {
        "01bWQ4TPGmsP6FS64nF4R9": 4
    },
    "death": {
        "014V6u9VubefjaPPl1QkTJ": 1
    },
    "derrièr": {
        "00X2yv2vrtritPt2CZnUTZ": 1
    },
    "des": {
        "00X2yv2vrtritPt2CZnUTZ": 3
    },
    "di": {
        "00X2yv2vrtritPt2CZnUTZ": 1
    },
    "diamond": {
        "01bWQ4TPGmsP6FS64nF4R9": 2
    },
    "dichter": {
        "01bWQ4TPGmsP6FS64nF4R9": 6
    },
    "dichterbij": {
        "01bWQ4TPGmsP6FS64nF4R9": 3
    },
    "die": {
        "014J7jX1wSv0manSdRnveo": 2,
        "01bWQ4TPGmsP6FS64nF4R9": 3
    },
    "differ": {
        "00YeYHw6zhoy1y7EPTgIkj": 3
    },
    "dinner": {
        "014V6u9VubefjaPPl1QkTJ": 1
    },
    "dis": {
        "00X2yv2vrtritPt2CZnUTZ": 1
    },
    "disco": {
        "00WIXhVVhswHuS6dlkScuw": 2
    },
    "disparaîtr": {
        "00X2yv2vrtritPt2CZnUTZ": 1
    },
    "do": {
        "00WIXhVVhswHuS6dlkScuw": 34,
        "00YeYHw6zhoy1y7EPTgIkj": 1,
        "00Z0GIRi0l7WqQnQJCo5S2": 32,
        "014J7jX1wSv0manSdRnveo": 2,
        "014V6u9VubefjaPPl1QkTJ": 4
    },
    "doe": {
        "014J7jX1wSv0manSdRnveo": 1,
        "01bWQ4TPGmsP6FS64nF4R9": 1
    },
    "doen": {
        "01bWQ4TPGmsP6FS64nF4R9": 1
    },
    "doll": {
        "012mGdSYIBEmERuScm2iOl": 1
    },
    "done": {
        "014V6u9VubefjaPPl1QkTJ": 1
    },
    "door": {
        "01bWQ4TPGmsP6FS64nF4R9": 1
    },
    "doubt": {
        "014V6u9VubefjaPPl1QkTJ": 1
    },
    "down": {
        "00YeYHw6zhoy1y7EPTgIkj": 1,
        "00Z0GIRi0l7WqQnQJCo5S2": 1,
        "014V6u9VubefjaPPl1QkTJ": 1,
        "01auWCuHXubb8KPZ0IXF4S": 3
    },
    "drawn": {
        "014V6u9VubefjaPPl1QkTJ": 1
    },
    "dring": {
        "00X2yv2vrtritPt2CZnUTZ": 18
    },
    "drink": {
        "00WIXhVVhswHuS6dlkScuw": 4
    },
    "drive": {
        "00Z0GIRi0l7WqQnQJCo5S2": 1,
        "011gUcrvLDn2gEApOdOhVe": 1,
        "01Bw3xiZ5PQfn0btMWICaQ": 2
    },
    "drum": {
        "012mGdSYIBEmERuScm2iOl": 1
    },
    "du": {
        "00X2yv2vrtritPt2CZnUTZ": 1
    },
    "edit": {
        "00Z0GIRi0l7WqQnQJCo5S2": 1,
        "01auWCuHXubb8KPZ0IXF4S": 1
    },
    "edm": {
        "014J7jX1wSv0manSdRnveo": 2,
        "01auWCuHXubb8KPZ0IXF4S": 1
    },
    "een": {
        "01bWQ4TPGmsP6FS64nF4R9": 3
    },
    "electro": {
        "01auWCuHXubb8KPZ0IXF4S": 1
    },
    "eleph": {
        "012mGdSYIBEmERuScm2iOl": 1
    },
    "ell": {
        "00X2yv2vrtritPt2CZnUTZ": 2
    },
    "els": {
        "014V6u9VubefjaPPl1QkTJ": 1
    },
    "eminem": {
        "014V6u9VubefjaPPl1QkTJ": 1
    },
    "emot": {
        "014V6u9VubefjaPPl1QkTJ": 1
    },
    "end": {
        "014V6u9VubefjaPPl1QkTJ": 1
    },
    "ene": {
        "01bWQ4TPGmsP6FS64nF4R9": 1
    },
    "engag": {
        "014V6u9VubefjaPPl1QkTJ": 1
    },
    "enough": {
        "00Z0GIRi0l7WqQnQJCo5S2": 3
    },
    "est": {
        "00X2yv2vrtritPt2CZnUTZ": 1
    },
    "et": {
        "00X2yv2vrtritPt2CZnUTZ": 2
    },
    "even": {
        "00Z0GIRi0l7WqQnQJCo5S2": 3,
        "014V6u9VubefjaPPl1QkTJ": 1
    },
    "ever": {
        "00WIXhVVhswHuS6dlkScuw": 6,
        "00YeYHw6zhoy1y7EPTgIkj": 1,
        "014V6u9VubefjaPPl1QkTJ": 3
    },
    "everi": {
        "014V6u9VubefjaPPl1QkTJ": 8
    },
    "evolv": {
        "014V6u9VubefjaPPl1QkTJ": 1
    },
    "eye": {
        "00YeYHw6zhoy1y7EPTgIkj": 1
    },
    "face": {
        "00YeYHw6zhoy1y7EPTgIkj": 1,
        "014V6u9VubefjaPPl1QkTJ": 1
    },
    "fact": {
        "014V6u9VubefjaPPl1QkTJ": 1
    },
    "fai": {
        "00X2yv2vrtritPt2CZnUTZ": 1
    },
    "fair": {
        "00X2yv2vrtritPt2CZnUTZ": 1
    },
    "fait": {
        "00X2yv2vrtritPt2CZnUTZ": 4
    },
    "fall": {
        "00YeYHw6zhoy1y7EPTgIkj": 1
    },
    "fals": {
        "014V6u9VubefjaPPl1QkTJ": 1
    },
    "far": {
        "014J7jX1wSv0manSdRnveo": 2
    },
    "fatboy": {
        "00WIXhVVhswHuS6dlkScuw": 2
    },
    "favorit": {
        "00YeYHw6zhoy1y7EPTgIkj": 2
    },
    "feel": {
        "014V6u9VubefjaPPl1QkTJ": 4
    },
    "feelin": {
        "014V6u9VubefjaPPl1QkTJ": 1
    },
    "feit": {
        "01bWQ4TPGmsP6FS64nF4R9": 3
    },
    "feldt": {
        "011gUcrvLDn2gEApOdOhVe": 1
    },
    "feu": {
        "00X2yv2vrtritPt2CZnUTZ": 1
    },
    "fight": {
        "014V6u9VubefjaPPl1QkTJ": 1
    },
    "fill": {
        "01bWQ4TPGmsP6FS64nF4R9": 2
    },
    "find": {
        "00YeYHw6zhoy1y7EPTgIkj": 7,
        "012mGdSYIBEmERuScm2iOl": 1,
        "014V6u9VubefjaPPl1QkTJ": 3
    },
    "fist": {
        "014V6u9VubefjaPPl1QkTJ": 1
    },
    "flat": {
        "014V6u9VubefjaPPl1QkTJ": 1
    },
    "fli": {
        "00YeYHw6zhoy1y7EPTgIkj": 2
    },
    "flicaill": {
        "00X2yv2vrtritPt2CZnUTZ": 1
    },
    "flintston": {
        "00WIXhVVhswHuS6dlkScuw": 2
    },
    "flip": {
        "00WIXhVVhswHuS6dlkScuw": 2
    },
    "float": {
        "014V6u9VubefjaPPl1QkTJ": 1
    },
    "fluid": {
        "014V6u9VubefjaPPl1QkTJ": 1
    },
    "fo": {
        "00WIXhVVhswHuS6dlkScuw": 4
    },
    "foam": {
        "014V6u9VubefjaPPl1QkTJ": 1
    },
    "fofana": {
        "00X2yv2vrtritPt2CZnUTZ": 1
    },
    "follow": {
        "01Bw3xiZ5PQfn0btMWICaQ": 6
    },
    "for": {
        "00WIXhVVhswHuS6dlkScuw": 2,
        "00YeYHw6zhoy1y7EPTgIkj": 6,
        "011gUcrvLDn2gEApOdOhVe": 6,
        "012mGdSYIBEmERuScm2iOl": 2,
        "014J7jX1wSv0manSdRnveo": 1
    },
    "forev": {
        "00YeYHw6zhoy1y7EPTgIkj": 4
    },
    "fought": {
        "014V6u9VubefjaPPl1QkTJ": 1
    },
    "fr": {
        "00X2yv2vrtritPt2CZnUTZ": 1
    },
    "franci": {
        "00YeYHw6zhoy1y7EPTgIkj": 1
    },
    "freeli": {
        "014V6u9VubefjaPPl1QkTJ": 1
    },
    "frenna": {
        "01bWQ4TPGmsP6FS64nF4R9": 1
    },
    "frequenc": {
        "01Bw3xiZ5PQfn0btMWICaQ": 1
    },
    "friend": {
        "014J7jX1wSv0manSdRnveo": 1
    },
    "from": {
        "00Z0GIRi0l7WqQnQJCo5S2": 1,
        "014V6u9VubefjaPPl1QkTJ": 4
    },
    "frères": {
        "00X2yv2vrtritPt2CZnUTZ": 1
    },
    "fuck": {
        "014V6u9VubefjaPPl1QkTJ": 2
    },
    "fuckin": {
        "014V6u9VubefjaPPl1QkTJ": 3
    },
    "fuel": {
        "014V6u9VubefjaPPl1QkTJ": 2
    },
    "fumé": {
        "00X2yv2vrtritPt2CZnUTZ": 1
    },
    "furthest": {
        "00YeYHw6zhoy1y7EPTgIkj": 1
    },
    "gang": {
        "00X2yv2vrtritPt2CZnUTZ": 2
    },
    "gangsta": {
        "014V6u9VubefjaPPl1QkTJ": 1
    },
    "gangster": {
        "014V6u9VubefjaPPl1QkTJ": 1
    },
    "get": {
        "00WIXhVVhswHuS6dlkScuw": 2,
        "00Z0GIRi0l7WqQnQJCo5S2": 6,
        "014V6u9VubefjaPPl1QkTJ": 3,
        "01auWCuHXubb8KPZ0IXF4S": 4
    },
    "giant": {
        "014V6u9VubefjaPPl1QkTJ": 1
    },
    "girl": {
        "00X2yv2vrtritPt2CZnUTZ": 4
    },
    "give": {
        "00Z0GIRi0l7WqQnQJCo5S2": 3,
        "014J7jX1wSv0manSdRnveo": 4,
        "014V6u9VubefjaPPl1QkTJ": 2
    },
    "go": {
        "00WIXhVVhswHuS6dlkScuw": 4,
        "00Z0GIRi0l7WqQnQJCo5S2": 3,
        "011gUcrvLDn2gEApOdOhVe": 4,
        "014V6u9VubefjaPPl1QkTJ": 7,
        "01Bw3xiZ5PQfn0btMWICaQ": 5
    },
    "goe": {
        "00YeYHw6zhoy1y7EPTgIkj": 1,
        "00Z0GIRi0l7WqQnQJCo5S2": 1
    },
    "gold": {
        "00WIXhVVhswHuS6dlkScuw": 4
    },
    "gon": {
        "00WIXhVVhswHuS6dlkScuw": 2,
        "00Z0GIRi0l7WqQnQJCo5S2": 1,
        "012mGdSYIBEmERuScm2iOl": 1,
        "014V6u9VubefjaPPl1QkTJ": 9
    },
    "gone": {
        "014V6u9VubefjaPPl1QkTJ": 2
    },
    "good": {
        "00WIXhVVhswHuS6dlkScuw": 6,
        "012mGdSYIBEmERuScm2iOl": 5,
        "01bWQ4TPGmsP6FS64nF4R9": 1
    },
    "goodby": {
        "014J7jX1wSv0manSdRnveo": 1
    },
    "got": {
        "00WIXhVVhswHuS6dlkScuw": 4,
        "00YeYHw6zhoy1y7EPTgIkj": 1,
        "00Z0GIRi0l7WqQnQJCo5S2": 1,
        "014J7jX1wSv0manSdRnveo": 2,
        "014V6u9VubefjaPPl1QkTJ": 5
    },
    "gross": {
        "00X2yv2vrtritPt2CZnUTZ": 1
    },
    "ground": {
        "014V6u9VubefjaPPl1QkTJ": 1
    },
    "groupi": {
        "00X2yv2vrtritPt2CZnUTZ": 1
    },
    "growin": {
        "014V6u9VubefjaPPl1QkTJ": 1
    },
    "guilt": {
        "014V6u9VubefjaPPl1QkTJ": 1
    },
    "gunpowd": {
        "014V6u9VubefjaPPl1QkTJ": 1
    },
    "guy": {
        "014J7jX1wSv0manSdRnveo": 4
    },
    "had": {
        "014V6u9VubefjaPPl1QkTJ": 1
    },
    "half": {
        "014V6u9VubefjaPPl1QkTJ": 1
    },
    "hand": {
        "014V6u9VubefjaPPl1QkTJ": 2
    },
    "hang": {
        "014V6u9VubefjaPPl1QkTJ": 1
    },
    "hard": {
        "00Z0GIRi0l7WqQnQJCo5S2": 3
    },
    "has": {
        "00YeYHw6zhoy1y7EPTgIkj": 1,
        "014V6u9VubefjaPPl1QkTJ": 1
    },
    "have": {
        "00Z0GIRi0l7WqQnQJCo5S2": 1,
        "011gUcrvLDn2gEApOdOhVe": 6,
        "014V6u9VubefjaPPl1QkTJ": 2
    },
    "heal": {
        "00Z0GIRi0l7WqQnQJCo5S2": 3
    },
    "heart": {
        "00YeYHw6zhoy1y7EPTgIkj": 4,
        "00Z0GIRi0l7WqQnQJCo5S2": 19
    },
    "heb": {
        "01bWQ4TPGmsP6FS64nF4R9": 2
    },
    "heeft": {
        "01bWQ4TPGmsP6FS64nF4R9": 1
    },
    "heen": {
        "01bWQ4TPGmsP6FS64nF4R9": 1
    },
    "hell": {
        "00Z0GIRi0l7WqQnQJCo5S2": 3,
        "014V6u9VubefjaPPl1QkTJ": 1
    },
    "hello": {
        "00X2yv2vrtritPt2CZnUTZ": 4
    },
    "henki": {
        "01bWQ4TPGmsP6FS64nF4R9": 1
    },
    "her": {
        "014J7jX1wSv0manSdRnveo": 4
    },
    "here": {
        "011gUcrvLDn2gEApOdOhVe": 3,
        "014J7jX1wSv0manSdRnveo": 5
    },
    "het": {
        "01bWQ4TPGmsP6FS64nF4R9": 8
    },
    "high": {
        "00Z0GIRi0l7WqQnQJCo5S2": 6,
        "01Bw3xiZ5PQfn0btMWICaQ": 4
    },
    "hijo": {
        "00X2yv2vrtritPt2CZnUTZ": 1
    },
    "hill": {
        "014V6u9VubefjaPPl1QkTJ": 1
    },
    "hip": {
        "00WIXhVVhswHuS6dlkScuw": 2,
        "01bWQ4TPGmsP6FS64nF4R9": 1
    },
    "hit": {
        "014V6u9VubefjaPPl1QkTJ": 1
    },
    "hola": {
        "00X2yv2vrtritPt2CZnUTZ": 8
    },
    "hold": {
        "014V6u9VubefjaPPl1QkTJ": 1
    },
    "home": {
        "014J7jX1wSv0manSdRnveo": 4
    },
    "honéon": {
        "00X2yv2vrtritPt2CZnUTZ": 1
    },
    "hoo": {
        "012mGdSYIBEmERuScm2iOl": 4
    },
    "hope": {
        "00YeYHw6zhoy1y7EPTgIkj": 7
    },
    "horn": {
        "012mGdSYIBEmERuScm2iOl": 1
    },
    "hot": {
        "00WIXhVVhswHuS6dlkScuw": 37
    },
    "hottest": {
        "00WIXhVVhswHuS6dlkScuw": 6
    },
    "hous": {
        "00YeYHw6zhoy1y7EPTgIkj": 1
    },
    "how": {
        "00WIXhVVhswHuS6dlkScuw": 6,
        "011gUcrvLDn2gEApOdOhVe": 4,
        "014V6u9VubefjaPPl1QkTJ": 7
    },
    "howev": {
        "014V6u9VubefjaPPl1QkTJ": 4
    },
    "hsmn": {
        "01bWQ4TPGmsP6FS64nF4R9": 1
    },
    "hurt": {
        "00Z0GIRi0l7WqQnQJCo5S2": 4
    },
    "i": {
        "00WIXhVVhswHuS6dlkScuw": 32,
        "00YeYHw6zhoy1y7EPTgIkj": 16,
        "00Z0GIRi0l7WqQnQJCo5S2": 1,
        "011gUcrvLDn2gEApOdOhVe": 8,
        "012mGdSYIBEmERuScm2iOl": 2,
        "014J7jX1wSv0manSdRnveo": 29,
        "014V6u9VubefjaPPl1QkTJ": 58,
        "01Bw3xiZ5PQfn0btMWICaQ": 6
    },
    "ietsj": {
        "01bWQ4TPGmsP6FS64nF4R9": 3
    },
    "if": {
        "00WIXhVVhswHuS6dlkScuw": 4,
        "012mGdSYIBEmERuScm2iOl": 1,
        "014V6u9VubefjaPPl1QkTJ": 1
    },
    "igo": {
        "00X2yv2vrtritPt2CZnUTZ": 1
    },
    "ik": {
        "01bWQ4TPGmsP6FS64nF4R9": 13
    },
    "illuminati": {
        "00WIXhVVhswHuS6dlkScuw": 4
    },
    "imposs": {
        "014V6u9VubefjaPPl1QkTJ": 4
    },
    "in": {
        "00YeYHw6zhoy1y7EPTgIkj": 2,
        "00Z0GIRi0l7WqQnQJCo5S2": 2,
        "014J7jX1wSv0manSdRnveo": 5,
        "014V6u9VubefjaPPl1QkTJ": 10,
        "01Bw3xiZ5PQfn0btMWICaQ": 2,
        "01bWQ4TPGmsP6FS64nF4R9": 10
    },
    "indi": {
        "00YeYHw6zhoy1y7EPTgIkj": 1,
        "011gUcrvLDn2gEApOdOhVe": 1
    },
    "info": {
        "00WIXhVVhswHuS6dlkScuw": 2
    },
    "insid": {
        "014V6u9VubefjaPPl1QkTJ": 1
    },
    "inspir": {
        "014V6u9VubefjaPPl1QkTJ": 1
    },
    "into": {
        "014V6u9VubefjaPPl1QkTJ": 3
    },
    "is": {
        "00YeYHw6zhoy1y7EPTgIkj": 4,
        "00Z0GIRi0l7WqQnQJCo5S2": 1,
        "012mGdSYIBEmERuScm2iOl": 21,
        "014V6u9VubefjaPPl1QkTJ": 12,
        "01bWQ4TPGmsP6FS64nF4R9": 11
    },
    "it": {
        "00WIXhVVhswHuS6dlkScuw": 28,
        "00YeYHw6zhoy1y7EPTgIkj": 2,
        "00Z0GIRi0l7WqQnQJCo5S2": 42,
        "011gUcrvLDn2gEApOdOhVe": 2,
        "012mGdSYIBEmERuScm2iOl": 1,
        "014J7jX1wSv0manSdRnveo": 6,
        "014V6u9VubefjaPPl1QkTJ": 31,
        "01Bw3xiZ5PQfn0btMWICaQ": 1
    },
    "ja": {
        "01bWQ4TPGmsP6FS64nF4R9": 4
    },
    "jackson": {
        "012mGdSYIBEmERuScm2iOl": 1
    },
    "je": {
        "00X2yv2vrtritPt2CZnUTZ": 6,
        "01bWQ4TPGmsP6FS64nF4R9": 7
    },
    "jij": {
        "01bWQ4TPGmsP6FS64nF4R9": 17
    },
    "jong": {
        "01bWQ4TPGmsP6FS64nF4R9": 3
    },
    "jou": {
        "01bWQ4TPGmsP6FS64nF4R9": 1
    },
    "journé": {
        "00X2yv2vrtritPt2CZnUTZ": 1
    },
    "juggernaut": {
        "014V6u9VubefjaPPl1QkTJ": 1
    },
    "just": {
        "00YeYHw6zhoy1y7EPTgIkj": 1,
        "014J7jX1wSv0manSdRnveo": 3,
        "014V6u9VubefjaPPl1QkTJ": 4
    },
    "keep": {
        "014J7jX1wSv0manSdRnveo": 4,
        "014V6u9VubefjaPPl1QkTJ": 2
    },
    "kiddi": {
        "012mGdSYIBEmERuScm2iOl": 1
    },
    "kijk": {
        "01bWQ4TPGmsP6FS64nF4R9": 1
    },
    "kill": {
        "00Z0GIRi0l7WqQnQJCo5S2": 3,
        "014V6u9VubefjaPPl1QkTJ": 1
    },
    "kiss": {
        "00YeYHw6zhoy1y7EPTgIkj": 1,
        "014J7jX1wSv0manSdRnveo": 4
    },
    "klaar": {
        "01bWQ4TPGmsP6FS64nF4R9": 2
    },
    "knife": {
        "014V6u9VubefjaPPl1QkTJ": 1
    },
    "know": {
        "00YeYHw6zhoy1y7EPTgIkj": 2,
        "00Z0GIRi0l7WqQnQJCo5S2": 1,
        "012mGdSYIBEmERuScm2iOl": 2,
        "014J7jX1wSv0manSdRnveo": 2,
        "014V6u9VubefjaPPl1QkTJ": 1
    },
    "knowin": {
        "014V6u9VubefjaPPl1QkTJ": 1
    },
    "kom": {
        "01bWQ4TPGmsP6FS64nF4R9": 9
    },
    "kremont": {
        "01auWCuHXubb8KPZ0IXF4S": 1
    },
    "kygo": {
        "00YeYHw6zhoy1y7EPTgIkj": 2
    },
    "larm": {
        "00X2yv2vrtritPt2CZnUTZ": 2
    },
    "last": {
        "014V6u9VubefjaPPl1QkTJ": 1
    },
    "latin": {
        "01Bw3xiZ5PQfn0btMWICaQ": 1,
        "01bWQ4TPGmsP6FS64nF4R9": 2
    },
    "lay": {
        "014V6u9VubefjaPPl1QkTJ": 1
    },
    "learnt": {
        "00Z0GIRi0l7WqQnQJCo5S2": 1
    },
    "left": {
        "00Z0GIRi0l7WqQnQJCo5S2": 1,
        "014V6u9VubefjaPPl1QkTJ": 3
    },
    "leftwich": {
        "00YeYHw6zhoy1y7EPTgIkj": 1
    },
    "legend": {
        "014V6u9VubefjaPPl1QkTJ": 1
    },
    "legendari": {
        "014V6u9VubefjaPPl1QkTJ": 1
    },
    "length": {
        "014V6u9VubefjaPPl1QkTJ": 4
    },
    "let": {
        "00Z0GIRi0l7WqQnQJCo5S2": 26,
        "011gUcrvLDn2gEApOdOhVe": 7,
        "014V6u9VubefjaPPl1QkTJ": 1
    },
    "lichten": {
        "01bWQ4TPGmsP6FS64nF4R9": 1
    },
    "liefst": {
        "01bWQ4TPGmsP6FS64nF4R9": 1
    },
    "life": {
        "00Z0GIRi0l7WqQnQJCo5S2": 3,
        "014V6u9VubefjaPPl1QkTJ": 1,
        "01Bw3xiZ5PQfn0btMWICaQ": 7
    },
    "light": {
        "00YeYHw6zhoy1y7EPTgIkj": 3,
        "014J7jX1wSv0manSdRnveo": 2
    },
    "like": {
        "00WIXhVVhswHuS6dlkScuw": 38,
        "00Z0GIRi0l7WqQnQJCo5S2": 3,
        "014V6u9VubefjaPPl1QkTJ": 11
    },
    "line": {
        "014J7jX1wSv0manSdRnveo": 1
    },
    "list": {
        "012mGdSYIBEmERuScm2iOl": 1
    },
    "litron": {
        "00X2yv2vrtritPt2CZnUTZ": 1
    },
    "littl": {
        "012mGdSYIBEmERuScm2iOl": 2,
        "014V6u9VubefjaPPl1QkTJ": 1
    },
    "live": {
        "00YeYHw6zhoy1y7EPTgIkj": 1,
        "014V6u9VubefjaPPl1QkTJ": 1
    },
    "london": {
        "00Z0GIRi0l7WqQnQJCo5S2": 1
    },
    "long": {
        "014V6u9VubefjaPPl1QkTJ": 4
    },
    "look": {
        "00WIXhVVhswHuS6dlkScuw": 12,
        "00YeYHw6zhoy1y7EPTgIkj": 4,
        "014V6u9VubefjaPPl1QkTJ": 1
    },
    "lost": {
        "01Bw3xiZ5PQfn0btMWICaQ": 1
    },
    "loui": {
        "00Z0GIRi0l7WqQnQJCo5S2": 1
    },
    "love": {
        "00YeYHw6zhoy1y7EPTgIkj": 3,
        "00Z0GIRi0l7WqQnQJCo5S2": 3,
        "014J7jX1wSv0manSdRnveo": 1
    },
    "lover": {
        "011gUcrvLDn2gEApOdOhVe": 1
    },
    "lovin": {
        "00WIXhVVhswHuS6dlkScuw": 4
    },
    "low": {
        "00Z0GIRi0l7WqQnQJCo5S2": 6,
        "01Bw3xiZ5PQfn0btMWICaQ": 6
    },
    "lung": {
        "014V6u9VubefjaPPl1QkTJ": 4
    },
    "ma": {
        "00X2yv2vrtritPt2CZnUTZ": 2
    },
    "madr": {
        "00X2yv2vrtritPt2CZnUTZ": 1
    },
    "make": {
        "012mGdSYIBEmERuScm2iOl": 1,
        "014V6u9VubefjaPPl1QkTJ": 5
    },
    "makin": {
        "014V6u9VubefjaPPl1QkTJ": 3
    },
    "man": {
        "014V6u9VubefjaPPl1QkTJ": 1
    },
    "manag": {
        "014V6u9VubefjaPPl1QkTJ": 1
    },
    "martha": {
        "014V6u9VubefjaPPl1QkTJ": 1
    },
    "match": {
        "014V6u9VubefjaPPl1QkTJ": 2
    },
    "merk": {
        "01auWCuHXubb8KPZ0IXF4S": 1
    },
    "mess": {
        "00Z0GIRi0l7WqQnQJCo5S2": 3,
        "014J7jX1wSv0manSdRnveo": 1
    },
    "messiest": {
        "014V6u9VubefjaPPl1QkTJ": 1
    },
    "met": {
        "01bWQ4TPGmsP6FS64nF4R9": 3
    },
    "mia": {
        "00X2yv2vrtritPt2CZnUTZ": 1
    },
    "mic": {
        "014V6u9VubefjaPPl1QkTJ": 1
    },
    "mien": {
        "00X2yv2vrtritPt2CZnUTZ": 1
    },
    "might": {
        "014V6u9VubefjaPPl1QkTJ": 1
    },
    "mij": {
        "01bWQ4TPGmsP6FS64nF4R9": 8
    },
    "mind": {
        "011gUcrvLDn2gEApOdOhVe": 1
    },
    "missin": {
        "00WIXhVVhswHuS6dlkScuw": 4
    },
    "mogen": {
        "01bWQ4TPGmsP6FS64nF4R9": 1
    },
    "mon": {
        "00X2yv2vrtritPt2CZnUTZ": 2
    },
    "mond": {
        "00X2yv2vrtritPt2CZnUTZ": 1
    },
    "monster": {
        "014V6u9VubefjaPPl1QkTJ": 4
    },
    "more": {
        "00YeYHw6zhoy1y7EPTgIkj": 4,
        "012mGdSYIBEmERuScm2iOl": 1,
        "014V6u9VubefjaPPl1QkTJ": 1
    },
    "morn": {
        "00YeYHw6zhoy1y7EPTgIkj": 3
    },
    "motherfucka": {
        "00WIXhVVhswHuS6dlkScuw": 6
    },
    "motherfuckin": {
        "014V6u9VubefjaPPl1QkTJ": 1
    },
    "motion": {
        "014V6u9VubefjaPPl1QkTJ": 1,
        "01bWQ4TPGmsP6FS64nF4R9": 1
    },
    "mouah": {
        "00X2yv2vrtritPt2CZnUTZ": 1
    },
    "mountain": {
        "01Bw3xiZ5PQfn0btMWICaQ": 4
    },
    "mouth": {
        "014V6u9VubefjaPPl1QkTJ": 1
    },
    "move": {
        "00WIXhVVhswHuS6dlkScuw": 4
    },
    "much": {
        "00WIXhVVhswHuS6dlkScuw": 4,
        "00Z0GIRi0l7WqQnQJCo5S2": 3
    },
    "music": {
        "014J7jX1wSv0manSdRnveo": 2,
        "014V6u9VubefjaPPl1QkTJ": 1
    },
    "my": {
        "00WIXhVVhswHuS6dlkScuw": 4,
        "011gUcrvLDn2gEApOdOhVe": 1,
        "014J7jX1wSv0manSdRnveo": 11,
        "014V6u9VubefjaPPl1QkTJ": 13,
        "01bWQ4TPGmsP6FS64nF4R9": 9
    },
    "myself": {
        "014J7jX1wSv0manSdRnveo": 1,
        "014V6u9VubefjaPPl1QkTJ": 3
    },
    "mère": {
        "00X2yv2vrtritPt2CZnUTZ": 1
    },
    "na": {
        "00WIXhVVhswHuS6dlkScuw": 4,
        "00Z0GIRi0l7WqQnQJCo5S2": 1,
        "012mGdSYIBEmERuScm2iOl": 1,
        "014J7jX1wSv0manSdRnveo": 1,
        "014V6u9VubefjaPPl1QkTJ": 8
    },
    "nacht": {
        "01bWQ4TPGmsP6FS64nF4R9": 3
    },
    "nah": {
        "014J7jX1wSv0manSdRnveo": 2
    },
    "nake": {
        "011gUcrvLDn2gEApOdOhVe": 3
    },
    "name": {
        "00YeYHw6zhoy1y7EPTgIkj": 1
    },
    "naughti": {
        "012mGdSYIBEmERuScm2iOl": 1
    },
    "near": {
        "014J7jX1wSv0manSdRnveo": 2
    },
    "nek": {
        "01bWQ4TPGmsP6FS64nF4R9": 2
    },
    "neo": {
        "012mGdSYIBEmERuScm2iOl": 1
    },
    "never": {
        "014V6u9VubefjaPPl1QkTJ": 6
    },
    "new": {
        "00WIXhVVhswHuS6dlkScuw": 2,
        "00Z0GIRi0l7WqQnQJCo5S2": 1,
        "014J7jX1wSv0manSdRnveo": 1
    },
    "nice": {
        "012mGdSYIBEmERuScm2iOl": 1
    },
    "nick": {
        "01bWQ4TPGmsP6FS64nF4R9": 1
    },
    "niemand": {
        "01bWQ4TPGmsP6FS64nF4R9": 1
    },
    "niet": {
        "01bWQ4TPGmsP6FS64nF4R9": 2
    },
    "night": {
        "014J7jX1wSv0manSdRnveo": 1
    },
    "nl": {
        "01bWQ4TPGmsP6FS64nF4R9": 1
    },
    "nobodi": {
        "014V6u9VubefjaPPl1QkTJ": 1
    },
    "nog": {
        "01bWQ4TPGmsP6FS64nF4R9": 4
    },
    "noir": {
        "00X2yv2vrtritPt2CZnUTZ": 1
    },
    "not": {
        "00Z0GIRi0l7WqQnQJCo5S2": 3,
        "012mGdSYIBEmERuScm2iOl": 4,
        "014J7jX1wSv0manSdRnveo": 4
    },
    "noth": {
        "014V6u9VubefjaPPl1QkTJ": 1
    },
    "nous": {
        "00X2yv2vrtritPt2CZnUTZ": 1
    },
    "now": {
        "00YeYHw6zhoy1y7EPTgIkj": 1,
        "012mGdSYIBEmERuScm2iOl": 1,
        "014V6u9VubefjaPPl1QkTJ": 4,
        "01auWCuHXubb8KPZ0IXF4S": 1
    },
    "number": {
        "012mGdSYIBEmERuScm2iOl": 1
    },
    "obsess": {
        "01bWQ4TPGmsP6FS64nF4R9": 1
    },
    "obstacl": {
        "014V6u9VubefjaPPl1QkTJ": 1
    },
    "of": {
        "00Z0GIRi0l7WqQnQJCo5S2": 3,
        "014J7jX1wSv0manSdRnveo": 1,
        "014V6u9VubefjaPPl1QkTJ": 11
    },
    "off": {
        "014V6u9VubefjaPPl1QkTJ": 2
    },
    "ogen": {
        "01bWQ4TPGmsP6FS64nF4R9": 3
    },
    "oh": {
        "00WIXhVVhswHuS6dlkScuw": 14,
        "00Z0GIRi0l7WqQnQJCo5S2": 18,
        "012mGdSYIBEmERuScm2iOl": 7,
        "014J7jX1wSv0manSdRnveo": 15,
        "014V6u9VubefjaPPl1QkTJ": 5
    },
    "ohh": {
        "014J7jX1wSv0manSdRnveo": 1
    },
    "om": {
        "01bWQ4TPGmsP6FS64nF4R9": 1
    },
    "on": {
        "00X2yv2vrtritPt2CZnUTZ": 4,
        "00YeYHw6zhoy1y7EPTgIkj": 4,
        "00Z0GIRi0l7WqQnQJCo5S2": 2,
        "014J7jX1wSv0manSdRnveo": 8,
        "014V6u9VubefjaPPl1QkTJ": 1,
        "01bWQ4TPGmsP6FS64nF4R9": 3
    },
    "one": {
        "00YeYHw6zhoy1y7EPTgIkj": 1,
        "012mGdSYIBEmERuScm2iOl": 1,
        "014V6u9VubefjaPPl1QkTJ": 2
    },
    "onli": {
        "014V6u9VubefjaPPl1QkTJ": 5,
        "01bWQ4TPGmsP6FS64nF4R9": 1
    },
    "ooh": {
        "014J7jX1wSv0manSdRnveo": 2
    },
    "oooh": {
        "014J7jX1wSv0manSdRnveo": 2
    },
    "open": {
        "00YeYHw6zhoy1y7EPTgIkj": 1
    },
    "or": {
        "012mGdSYIBEmERuScm2iOl": 1,
        "014V6u9VubefjaPPl1QkTJ": 2
    },
    "other": {
        "00Z0GIRi0l7WqQnQJCo5S2": 1
    },
    "ou": {
        "00X2yv2vrtritPt2CZnUTZ": 1
    },
    "ounc": {
        "014V6u9VubefjaPPl1QkTJ": 4
    },
    "our": {
        "00Z0GIRi0l7WqQnQJCo5S2": 1
    },
    "out": {
        "012mGdSYIBEmERuScm2iOl": 4,
        "014J7jX1wSv0manSdRnveo": 1,
        "014V6u9VubefjaPPl1QkTJ": 4
    },
    "over": {
        "014J7jX1wSv0manSdRnveo": 4
    },
    "own": {
        "014J7jX1wSv0manSdRnveo": 6
    },
    "par": {
        "00X2yv2vrtritPt2CZnUTZ": 2
    },
    "part": {
        "00Z0GIRi0l7WqQnQJCo5S2": 1
    },
    "parti": {
        "00WIXhVVhswHuS6dlkScuw": 4,
        "00X2yv2vrtritPt2CZnUTZ": 1
    },
    "pas": {
        "00X2yv2vrtritPt2CZnUTZ": 6
    },
    "pass": {
        "00X2yv2vrtritPt2CZnUTZ": 2,
        "00Z0GIRi0l7WqQnQJCo5S2": 1
    },
    "peep": {
        "00WIXhVVhswHuS6dlkScuw": 2
    },
    "pein": {
        "00X2yv2vrtritPt2CZnUTZ": 1
    },
    "pens": {
        "00X2yv2vrtritPt2CZnUTZ": 1
    },
    "persever": {
        "014V6u9VubefjaPPl1QkTJ": 1
    },
    "peur": {
        "00X2yv2vrtritPt2CZnUTZ": 1
    },
    "phenomen": {
        "014V6u9VubefjaPPl1QkTJ": 18
    },
    "pictur": {
        "014V6u9VubefjaPPl1QkTJ": 2
    },
    "pl": {
        "01auWCuHXubb8KPZ0IXF4S": 1
    },
    "place": {
        "00YeYHw6zhoy1y7EPTgIkj": 2,
        "00Z0GIRi0l7WqQnQJCo5S2": 1
    },
    "placemat": {
        "014V6u9VubefjaPPl1QkTJ": 1
    },
    "plastic": {
        "014V6u9VubefjaPPl1QkTJ": 1
    },
    "plate": {
        "014V6u9VubefjaPPl1QkTJ": 1
    },
    "plus": {
        "00X2yv2vrtritPt2CZnUTZ": 1
    },
    "pnl": {
        "00X2yv2vrtritPt2CZnUTZ": 2
    },
    "poke": {
        "01bWQ4TPGmsP6FS64nF4R9": 1
    },
    "polícia": {
        "00X2yv2vrtritPt2CZnUTZ": 1
    },
    "pooki": {
        "00X2yv2vrtritPt2CZnUTZ": 1
    },
    "pop": {
        "00WIXhVVhswHuS6dlkScuw": 1,
        "00YeYHw6zhoy1y7EPTgIkj": 1,
        "00Z0GIRi0l7WqQnQJCo5S2": 1,
        "011gUcrvLDn2gEApOdOhVe": 1,
        "014J7jX1wSv0manSdRnveo": 2
    },
    "poucav": {
        "00X2yv2vrtritPt2CZnUTZ": 1
    },
    "pour": {
        "00X2yv2vrtritPt2CZnUTZ": 1
    },
    "pout": {
        "012mGdSYIBEmERuScm2iOl": 2
    },
    "power": {
        "014V6u9VubefjaPPl1QkTJ": 1
    },
    "prepar": {
        "014V6u9VubefjaPPl1QkTJ": 1
    },
    "prevail": {
        "014V6u9VubefjaPPl1QkTJ": 1
    },
    "probabl": {
        "014V6u9VubefjaPPl1QkTJ": 1
    },
    "progress": {
        "01auWCuHXubb8KPZ0IXF4S": 1
    },
    "prove": {
        "014V6u9VubefjaPPl1QkTJ": 1
    },
    "pt": {
        "01bWQ4TPGmsP6FS64nF4R9": 1
    },
    "punch": {
        "014V6u9VubefjaPPl1QkTJ": 1
    },
    "purs": {
        "014V6u9VubefjaPPl1QkTJ": 1
    },
    "put": {
        "014V6u9VubefjaPPl1QkTJ": 5
    },
    "putain": {
        "00X2yv2vrtritPt2CZnUTZ": 1
    },
    "qlf": {
        "00X2yv2vrtritPt2CZnUTZ": 1
    },
    "quand": {
        "00X2yv2vrtritPt2CZnUTZ": 1
    },
    "r": {
        "00X2yv2vrtritPt2CZnUTZ": 1,
        "012mGdSYIBEmERuScm2iOl": 1
    },
    "racol": {
        "00X2yv2vrtritPt2CZnUTZ": 1
    },
    "radio": {
        "01auWCuHXubb8KPZ0IXF4S": 1
    },
    "rage": {
        "014V6u9VubefjaPPl1QkTJ": 1
    },
    "rap": {
        "014V6u9VubefjaPPl1QkTJ": 2
    },
    "rassuré": {
        "00X2yv2vrtritPt2CZnUTZ": 1
    },
    "readi": {
        "00WIXhVVhswHuS6dlkScuw": 4,
        "014V6u9VubefjaPPl1QkTJ": 2
    },
    "real": {
        "014V6u9VubefjaPPl1QkTJ": 1
    },
    "realm": {
        "014V6u9VubefjaPPl1QkTJ": 1
    },
    "relookésl": {
        "00X2yv2vrtritPt2CZnUTZ": 1
    },
    "remind": {
        "014V6u9VubefjaPPl1QkTJ": 1
    },
    "remix": {
        "00YeYHw6zhoy1y7EPTgIkj": 3,
        "011gUcrvLDn2gEApOdOhVe": 1,
        "014J7jX1wSv0manSdRnveo": 2
    },
    "rentrer": {
        "00X2yv2vrtritPt2CZnUTZ": 1
    },
    "reput": {
        "014V6u9VubefjaPPl1QkTJ": 1
    },
    "respond": {
        "014V6u9VubefjaPPl1QkTJ": 2
    },
    "retali": {
        "014V6u9VubefjaPPl1QkTJ": 1
    },
    "rhyme": {
        "014V6u9VubefjaPPl1QkTJ": 1
    },
    "rican": {
        "00X2yv2vrtritPt2CZnUTZ": 1
    },
    "right": {
        "014J7jX1wSv0manSdRnveo": 3
    },
    "river": {
        "01Bw3xiZ5PQfn0btMWICaQ": 4
    },
    "road": {
        "00Z0GIRi0l7WqQnQJCo5S2": 1
    },
    "rock": {
        "00WIXhVVhswHuS6dlkScuw": 2
    },
    "romário": {
        "00X2yv2vrtritPt2CZnUTZ": 1
    },
    "rough": {
        "014V6u9VubefjaPPl1QkTJ": 1
    },
    "run": {
        "011gUcrvLDn2gEApOdOhVe": 1
    },
    "runnin": {
        "014V6u9VubefjaPPl1QkTJ": 1
    },
    "sa": {
        "00X2yv2vrtritPt2CZnUTZ": 1
    },
    "sacrific": {
        "014V6u9VubefjaPPl1QkTJ": 1
    },
    "sad": {
        "00YeYHw6zhoy1y7EPTgIkj": 1
    },
    "said": {
        "014J7jX1wSv0manSdRnveo": 2
    },
    "sake": {
        "012mGdSYIBEmERuScm2iOl": 2
    },
    "saliv": {
        "014V6u9VubefjaPPl1QkTJ": 1
    },
    "sam": {
        "011gUcrvLDn2gEApOdOhVe": 1
    },
    "same": {
        "014V6u9VubefjaPPl1QkTJ": 2
    },
    "santa": {
        "012mGdSYIBEmERuScm2iOl": 21
    },
    "say": {
        "014J7jX1wSv0manSdRnveo": 1,
        "014V6u9VubefjaPPl1QkTJ": 7
    },
    "scott": {
        "014J7jX1wSv0manSdRnveo": 1
    },
    "scrap": {
        "014V6u9VubefjaPPl1QkTJ": 1
    },
    "screw": {
        "014V6u9VubefjaPPl1QkTJ": 1
    },
    "see": {
        "00WIXhVVhswHuS6dlkScuw": 4,
        "00YeYHw6zhoy1y7EPTgIkj": 1,
        "012mGdSYIBEmERuScm2iOl": 1,
        "014J7jX1wSv0manSdRnveo": 6
    },
    "seen": {
        "00WIXhVVhswHuS6dlkScuw": 6,
        "011gUcrvLDn2gEApOdOhVe": 6
    },
    "sentent": {
        "00X2yv2vrtritPt2CZnUTZ": 1
    },
    "set": {
        "014V6u9VubefjaPPl1QkTJ": 1
    },
    "seven": {
        "00Z0GIRi0l7WqQnQJCo5S2": 1
    },
    "shade": {
        "01bWQ4TPGmsP6FS64nF4R9": 1
    },
    "she": {
        "014J7jX1wSv0manSdRnveo": 2,
        "01Bw3xiZ5PQfn0btMWICaQ": 1
    },
    "sheitana": {
        "00X2yv2vrtritPt2CZnUTZ": 1
    },
    "shelf": {
        "014V6u9VubefjaPPl1QkTJ": 1
    },
    "shield": {
        "014V6u9VubefjaPPl1QkTJ": 1
    },
    "shine": {
        "00YeYHw6zhoy1y7EPTgIkj": 7
    },
    "shit": {
        "014V6u9VubefjaPPl1QkTJ": 2
    },
    "shiv": {
        "014V6u9VubefjaPPl1QkTJ": 1
    },
    "sho": {
        "00WIXhVVhswHuS6dlkScuw": 4
    },
    "should": {
        "014V6u9VubefjaPPl1QkTJ": 1
    },
    "shove": {
        "014V6u9VubefjaPPl1QkTJ": 1
    },
    "show": {
        "014V6u9VubefjaPPl1QkTJ": 2
    },
    "shut": {
        "014V6u9VubefjaPPl1QkTJ": 1
    },
    "side": {
        "00Z0GIRi0l7WqQnQJCo5S2": 1
    },
    "sinc": {
        "011gUcrvLDn2gEApOdOhVe": 2
    },
    "sing": {
        "00YeYHw6zhoy1y7EPTgIkj": 3
    },
    "singl": {
        "00Z0GIRi0l7WqQnQJCo5S2": 1,
        "01bWQ4TPGmsP6FS64nF4R9": 1
    },
    "sippin": {
        "00WIXhVVhswHuS6dlkScuw": 4
    },
    "sissi": {
        "014V6u9VubefjaPPl1QkTJ": 1
    },
    "situat": {
        "014V6u9VubefjaPPl1QkTJ": 1
    },
    "sky": {
        "014J7jX1wSv0manSdRnveo": 1
    },
    "sleep": {
        "012mGdSYIBEmERuScm2iOl": 1
    },
    "slim": {
        "00WIXhVVhswHuS6dlkScuw": 2
    },
    "slip": {
        "014V6u9VubefjaPPl1QkTJ": 1
    },
    "smallest": {
        "014V6u9VubefjaPPl1QkTJ": 1
    },
    "smoke": {
        "00YeYHw6zhoy1y7EPTgIkj": 1
    },
    "snow": {
        "00YeYHw6zhoy1y7EPTgIkj": 1
    },
    "so": {
        "00WIXhVVhswHuS6dlkScuw": 6,
        "00YeYHw6zhoy1y7EPTgIkj": 9,
        "00Z0GIRi0l7WqQnQJCo5S2": 3,
        "012mGdSYIBEmERuScm2iOl": 1,
        "014J7jX1wSv0manSdRnveo": 5,
        "014V6u9VubefjaPPl1QkTJ": 1
    },
    "soir": {
        "00X2yv2vrtritPt2CZnUTZ": 1
    },
    "some": {
        "00WIXhVVhswHuS6dlkScuw": 2,
        "014V6u9VubefjaPPl1QkTJ": 1
    },
    "somebodi": {
        "014J7jX1wSv0manSdRnveo": 1
    },
    "someon": {
        "00Z0GIRi0l7WqQnQJCo5S2": 3
    },
    "someth": {
        "00WIXhVVhswHuS6dlkScuw": 2,
        "00Z0GIRi0l7WqQnQJCo5S2": 2
    },
    "sometim": {
        "014V6u9VubefjaPPl1QkTJ": 2
    },
    "song": {
        "00YeYHw6zhoy1y7EPTgIkj": 1
    },
    "songtekst": {
        "01bWQ4TPGmsP6FS64nF4R9": 1
    },
    "sont": {
        "00X2yv2vrtritPt2CZnUTZ": 1
    },
    "sor": {
        "00X2yv2vrtritPt2CZnUTZ": 2
    },
    "sound": {
        "00YeYHw6zhoy1y7EPTgIkj": 2,
        "00Z0GIRi0l7WqQnQJCo5S2": 1
    },
    "southpaw": {
        "014V6u9VubefjaPPl1QkTJ": 2
    },
    "spark": {
        "014V6u9VubefjaPPl1QkTJ": 1
    },
    "speed": {
        "00WIXhVVhswHuS6dlkScuw": 2
    },
    "spice": {
        "00WIXhVVhswHuS6dlkScuw": 4
    },
    "spin": {
        "014J7jX1wSv0manSdRnveo": 1
    },
    "sta": {
        "01bWQ4TPGmsP6FS64nF4R9": 1
    },
    "stand": {
        "00YeYHw6zhoy1y7EPTgIkj": 1,
        "014J7jX1wSv0manSdRnveo": 2
    },
    "statement": {
        "014V6u9VubefjaPPl1QkTJ": 1
    },
    "status": {
        "014V6u9VubefjaPPl1QkTJ": 1
    },
    "stay": {
        "014V6u9VubefjaPPl1QkTJ": 1
    },
    "steel": {
        "014V6u9VubefjaPPl1QkTJ": 1
    },
    "step": {
        "014V6u9VubefjaPPl1QkTJ": 1
    },
    "stewart": {
        "014V6u9VubefjaPPl1QkTJ": 1
    },
    "stick": {
        "014V6u9VubefjaPPl1QkTJ": 1
    },
    "stiletto": {
        "014J7jX1wSv0manSdRnveo": 1
    },
    "still": {
        "014J7jX1wSv0manSdRnveo": 2,
        "014V6u9VubefjaPPl1QkTJ": 1
    },
    "stomp": {
        "014V6u9VubefjaPPl1QkTJ": 1
    },
    "stop": {
        "014V6u9VubefjaPPl1QkTJ": 4
    },
    "strap": {
        "014V6u9VubefjaPPl1QkTJ": 1
    },
    "stuck": {
        "014V6u9VubefjaPPl1QkTJ": 1
    },
    "stupid": {
        "014J7jX1wSv0manSdRnveo": 1
    },
    "suav": {
        "01bWQ4TPGmsP6FS64nF4R9": 32
    },
    "subject": {
        "014V6u9VubefjaPPl1QkTJ": 1
    },
    "sui": {
        "00X2yv2vrtritPt2CZnUTZ": 2
    },
    "sun": {
        "00YeYHw6zhoy1y7EPTgIkj": 1
    },
    "sur": {
        "00X2yv2vrtritPt2CZnUTZ": 1
    },
    "survivor": {
        "014V6u9VubefjaPPl1QkTJ": 1
    },
    "switch": {
        "00WIXhVVhswHuS6dlkScuw": 2
    },
    "system": {
        "00WIXhVVhswHuS6dlkScuw": 2
    },
    "t": {
        "01bWQ4TPGmsP6FS64nF4R9": 1
    },
    "ta": {
        "00WIXhVVhswHuS6dlkScuw": 2,
        "00X2yv2vrtritPt2CZnUTZ": 2,
        "014J7jX1wSv0manSdRnveo": 1,
        "014V6u9VubefjaPPl1QkTJ": 2
    },
    "tabitha": {
        "01bWQ4TPGmsP6FS64nF4R9": 2
    },
    "take": {
        "00WIXhVVhswHuS6dlkScuw": 14,
        "00Z0GIRi0l7WqQnQJCo5S2": 3,
        "014J7jX1wSv0manSdRnveo": 4,
        "014V6u9VubefjaPPl1QkTJ": 7,
        "01Bw3xiZ5PQfn0btMWICaQ": 2
    },
    "tast": {
        "014V6u9VubefjaPPl1QkTJ": 1
    },
    "taught": {
        "014V6u9VubefjaPPl1QkTJ": 1
    },
    "tchiki": {
        "00X2yv2vrtritPt2CZnUTZ": 2
    },
    "tchikit": {
        "00X2yv2vrtritPt2CZnUTZ": 1
    },
    "te": {
        "00X2yv2vrtritPt2CZnUTZ": 4
    },
    "tear": {
        "00Z0GIRi0l7WqQnQJCo5S2": 6
    },
    "tech": {
        "00X2yv2vrtritPt2CZnUTZ": 1
    },
    "tell": {
        "012mGdSYIBEmERuScm2iOl": 2
    },
    "temp": {
        "00X2yv2vrtritPt2CZnUTZ": 1
    },
    "tempo": {
        "00WIXhVVhswHuS6dlkScuw": 2
    },
    "than": {
        "014J7jX1wSv0manSdRnveo": 1,
        "014V6u9VubefjaPPl1QkTJ": 1
    },
    "that": {
        "00WIXhVVhswHuS6dlkScuw": 18,
        "00YeYHw6zhoy1y7EPTgIkj": 4,
        "012mGdSYIBEmERuScm2iOl": 1,
        "014V6u9VubefjaPPl1QkTJ": 17
    },
    "the": {
        "00WIXhVVhswHuS6dlkScuw": 50,
        "00YeYHw6zhoy1y7EPTgIkj": 13,
        "00Z0GIRi0l7WqQnQJCo5S2": 8,
        "012mGdSYIBEmERuScm2iOl": 1,
        "014J7jX1wSv0manSdRnveo": 12,
        "014V6u9VubefjaPPl1QkTJ": 25,
        "01Bw3xiZ5PQfn0btMWICaQ": 2
    },
    "then": {
        "00WIXhVVhswHuS6dlkScuw": 2,
        "014V6u9VubefjaPPl1QkTJ": 2
    },
    "there": {
        "014J7jX1wSv0manSdRnveo": 1,
        "014V6u9VubefjaPPl1QkTJ": 1
    },
    "they": {
        "00Z0GIRi0l7WqQnQJCo5S2": 3,
        "014V6u9VubefjaPPl1QkTJ": 1
    },
    "thing": {
        "014V6u9VubefjaPPl1QkTJ": 3
    },
    "this": {
        "014V6u9VubefjaPPl1QkTJ": 1
    },
    "though": {
        "014V6u9VubefjaPPl1QkTJ": 5
    },
    "thought": {
        "014V6u9VubefjaPPl1QkTJ": 2
    },
    "through": {
        "014V6u9VubefjaPPl1QkTJ": 3
    },
    "throwin": {
        "014V6u9VubefjaPPl1QkTJ": 1
    },
    "time": {
        "00Z0GIRi0l7WqQnQJCo5S2": 6,
        "012mGdSYIBEmERuScm2iOl": 1,
        "014V6u9VubefjaPPl1QkTJ": 2
    },
    "tin": {
        "012mGdSYIBEmERuScm2iOl": 1
    },
    "tire": {
        "00X2yv2vrtritPt2CZnUTZ": 1
    },
    "tiësto": {
        "014J7jX1wSv0manSdRnveo": 2
    },
    "to": {
        "00WIXhVVhswHuS6dlkScuw": 4,
        "00YeYHw6zhoy1y7EPTgIkj": 2,
        "00Z0GIRi0l7WqQnQJCo5S2": 5,
        "012mGdSYIBEmERuScm2iOl": 21,
        "014J7jX1wSv0manSdRnveo": 1,
        "014V6u9VubefjaPPl1QkTJ": 31,
        "01Bw3xiZ5PQfn0btMWICaQ": 3
    },
    "tomlinson": {
        "00Z0GIRi0l7WqQnQJCo5S2": 1
    },
    "tongu": {
        "014V6u9VubefjaPPl1QkTJ": 1
    },
    "too": {
        "00Z0GIRi0l7WqQnQJCo5S2": 6,
        "012mGdSYIBEmERuScm2iOl": 1,
        "014V6u9VubefjaPPl1QkTJ": 1
    },
    "tootl": {
        "012mGdSYIBEmERuScm2iOl": 1
    },
    "tori": {
        "00X2yv2vrtritPt2CZnUTZ": 1
    },
    "touch": {
        "00WIXhVVhswHuS6dlkScuw": 2,
        "01bWQ4TPGmsP6FS64nF4R9": 9
    },
    "touchera": {
        "00X2yv2vrtritPt2CZnUTZ": 4
    },
    "tous": {
        "00X2yv2vrtritPt2CZnUTZ": 1
    },
    "tout": {
        "00X2yv2vrtritPt2CZnUTZ": 1
    },
    "town": {
        "012mGdSYIBEmERuScm2iOl": 21,
        "014J7jX1wSv0manSdRnveo": 1
    },
    "toy": {
        "012mGdSYIBEmERuScm2iOl": 1
    },
    "tri": {
        "014V6u9VubefjaPPl1QkTJ": 1
    },
    "tropic": {
        "01Bw3xiZ5PQfn0btMWICaQ": 1
    },
    "true": {
        "00YeYHw6zhoy1y7EPTgIkj": 3
    },
    "truth": {
        "00WIXhVVhswHuS6dlkScuw": 2
    },
    "tryin": {
        "014V6u9VubefjaPPl1QkTJ": 1
    },
    "tu": {
        "00X2yv2vrtritPt2CZnUTZ": 8
    },
    "turn": {
        "00YeYHw6zhoy1y7EPTgIkj": 1
    },
    "twenti": {
        "00Z0GIRi0l7WqQnQJCo5S2": 1
    },
    "twice": {
        "012mGdSYIBEmERuScm2iOl": 1,
        "014V6u9VubefjaPPl1QkTJ": 1
    },
    "tête": {
        "00X2yv2vrtritPt2CZnUTZ": 2
    },
    "uit": {
        "01bWQ4TPGmsP6FS64nF4R9": 1
    },
    "unchart": {
        "014V6u9VubefjaPPl1QkTJ": 1
    },
    "under": {
        "00Z0GIRi0l7WqQnQJCo5S2": 1,
        "014V6u9VubefjaPPl1QkTJ": 1
    },
    "une": {
        "00X2yv2vrtritPt2CZnUTZ": 2
    },
    "unknown": {
        "014V6u9VubefjaPPl1QkTJ": 2
    },
    "unpopp": {
        "014V6u9VubefjaPPl1QkTJ": 1
    },
    "unstopp": {
        "014V6u9VubefjaPPl1QkTJ": 1
    },
    "until": {
        "00YeYHw6zhoy1y7EPTgIkj": 1,
        "014V6u9VubefjaPPl1QkTJ": 5
    },
    "untopp": {
        "014V6u9VubefjaPPl1QkTJ": 1
    },
    "up": {
        "00Z0GIRi0l7WqQnQJCo5S2": 3,
        "014J7jX1wSv0manSdRnveo": 1,
        "014V6u9VubefjaPPl1QkTJ": 3
    },
    "uphil": {
        "014V6u9VubefjaPPl1QkTJ": 1
    },
    "urban": {
        "00X2yv2vrtritPt2CZnUTZ": 1
    },
    "use": {
        "014V6u9VubefjaPPl1QkTJ": 1
    },
    "vaart": {
        "01bWQ4TPGmsP6FS64nF4R9": 1
    },
    "valid": {
        "014V6u9VubefjaPPl1QkTJ": 1
    },
    "vall": {
        "01bWQ4TPGmsP6FS64nF4R9": 1
    },
    "valv": {
        "014V6u9VubefjaPPl1QkTJ": 1
    },
    "vers": {
        "014V6u9VubefjaPPl1QkTJ": 1
    },
    "veut": {
        "00X2yv2vrtritPt2CZnUTZ": 1
    },
    "vibe": {
        "01bWQ4TPGmsP6FS64nF4R9": 1
    },
    "villa": {
        "00X2yv2vrtritPt2CZnUTZ": 2
    },
    "violet": {
        "00X2yv2vrtritPt2CZnUTZ": 1
    },
    "vivr": {
        "00X2yv2vrtritPt2CZnUTZ": 1
    },
    "voir": {
        "00X2yv2vrtritPt2CZnUTZ": 1
    },
    "waar": {
        "01bWQ4TPGmsP6FS64nF4R9": 2
    },
    "waarop": {
        "01bWQ4TPGmsP6FS64nF4R9": 1
    },
    "wage": {
        "014V6u9VubefjaPPl1QkTJ": 1
    },
    "wagin": {
        "014V6u9VubefjaPPl1QkTJ": 1
    },
    "wait": {
        "00YeYHw6zhoy1y7EPTgIkj": 2
    },
    "waitin": {
        "014V6u9VubefjaPPl1QkTJ": 1
    },
    "wall": {
        "014V6u9VubefjaPPl1QkTJ": 2
    },
    "wallac": {
        "014V6u9VubefjaPPl1QkTJ": 1
    },
    "wan": {
        "00WIXhVVhswHuS6dlkScuw": 2,
        "014J7jX1wSv0manSdRnveo": 1
    },
    "want": {
        "00WIXhVVhswHuS6dlkScuw": 2,
        "014V6u9VubefjaPPl1QkTJ": 2,
        "01Bw3xiZ5PQfn0btMWICaQ": 1,
        "01bWQ4TPGmsP6FS64nF4R9": 6
    },
    "warm": {
        "00YeYHw6zhoy1y7EPTgIkj": 4
    },
    "was": {
        "014V6u9VubefjaPPl1QkTJ": 2
    },
    "wat": {
        "01bWQ4TPGmsP6FS64nF4R9": 10
    },
    "watch": {
        "012mGdSYIBEmERuScm2iOl": 3,
        "014J7jX1wSv0manSdRnveo": 4
    },
    "water": {
        "00YeYHw6zhoy1y7EPTgIkj": 1,
        "014V6u9VubefjaPPl1QkTJ": 1,
        "01bWQ4TPGmsP6FS64nF4R9": 1
    },
    "way": {
        "00WIXhVVhswHuS6dlkScuw": 4,
        "00YeYHw6zhoy1y7EPTgIkj": 1,
        "00Z0GIRi0l7WqQnQJCo5S2": 1,
        "014V6u9VubefjaPPl1QkTJ": 1
    },
    "we": {
        "00YeYHw6zhoy1y7EPTgIkj": 4,
        "00Z0GIRi0l7WqQnQJCo5S2": 1,
        "01bWQ4TPGmsP6FS64nF4R9": 1
    },
    "weet": {
        "01bWQ4TPGmsP6FS64nF4R9": 2
    },
    "well": {
        "014V6u9VubefjaPPl1QkTJ": 1
    },
    "wesh": {
        "00X2yv2vrtritPt2CZnUTZ": 6
    },
    "what": {
        "00WIXhVVhswHuS6dlkScuw": 4,
        "00YeYHw6zhoy1y7EPTgIkj": 4,
        "00Z0GIRi0l7WqQnQJCo5S2": 1,
        "014V6u9VubefjaPPl1QkTJ": 9
    },
    "whatev": {
        "00Z0GIRi0l7WqQnQJCo5S2": 6,
        "014V6u9VubefjaPPl1QkTJ": 4
    },
    "when": {
        "00Z0GIRi0l7WqQnQJCo5S2": 13,
        "012mGdSYIBEmERuScm2iOl": 2,
        "014V6u9VubefjaPPl1QkTJ": 4
    },
    "where": {
        "014J7jX1wSv0manSdRnveo": 1,
        "014V6u9VubefjaPPl1QkTJ": 2
    },
    "wherev": {
        "01Bw3xiZ5PQfn0btMWICaQ": 2
    },
    "whi": {
        "012mGdSYIBEmERuScm2iOl": 2,
        "014J7jX1wSv0manSdRnveo": 3
    },
    "while": {
        "011gUcrvLDn2gEApOdOhVe": 9
    },
    "who": {
        "00YeYHw6zhoy1y7EPTgIkj": 1,
        "012mGdSYIBEmERuScm2iOl": 1,
        "014V6u9VubefjaPPl1QkTJ": 4
    },
    "wield": {
        "014V6u9VubefjaPPl1QkTJ": 1
    },
    "wij": {
        "01bWQ4TPGmsP6FS64nF4R9": 1
    },
    "wil": {
        "01bWQ4TPGmsP6FS64nF4R9": 6
    },
    "will": {
        "014V6u9VubefjaPPl1QkTJ": 2
    },
    "winter": {
        "00YeYHw6zhoy1y7EPTgIkj": 1
    },
    "with": {
        "00YeYHw6zhoy1y7EPTgIkj": 7,
        "014V6u9VubefjaPPl1QkTJ": 13,
        "01Bw3xiZ5PQfn0btMWICaQ": 2,
        "01bWQ4TPGmsP6FS64nF4R9": 2
    },
    "without": {
        "00YeYHw6zhoy1y7EPTgIkj": 2
    },
    "wo": {
        "014V6u9VubefjaPPl1QkTJ": 4
    },
    "wonder": {
        "014V6u9VubefjaPPl1QkTJ": 1
    },
    "woo": {
        "012mGdSYIBEmERuScm2iOl": 4
    },
    "work": {
        "014V6u9VubefjaPPl1QkTJ": 1
    },
    "worst": {
        "014V6u9VubefjaPPl1QkTJ": 1
    },
    "wou": {
        "01bWQ4TPGmsP6FS64nF4R9": 1
    },
    "wrap": {
        "00YeYHw6zhoy1y7EPTgIkj": 1
    },
    "write": {
        "014V6u9VubefjaPPl1QkTJ": 1
    },
    "yeah": {
        "00WIXhVVhswHuS6dlkScuw": 2,
        "00YeYHw6zhoy1y7EPTgIkj": 1,
        "00Z0GIRi0l7WqQnQJCo5S2": 1,
        "012mGdSYIBEmERuScm2iOl": 4,
        "014J7jX1wSv0manSdRnveo": 2,
        "014V6u9VubefjaPPl1QkTJ": 1
    },
    "yema": {
        "00X2yv2vrtritPt2CZnUTZ": 4
    },
    "york": {
        "00Z0GIRi0l7WqQnQJCo5S2": 1
    },
    "you": {
        "00WIXhVVhswHuS6dlkScuw": 56,
        "00YeYHw6zhoy1y7EPTgIkj": 26,
        "00Z0GIRi0l7WqQnQJCo5S2": 30,
        "011gUcrvLDn2gEApOdOhVe": 14,
        "012mGdSYIBEmERuScm2iOl": 11,
        "014J7jX1wSv0manSdRnveo": 16,
        "014V6u9VubefjaPPl1QkTJ": 36,
        "01Bw3xiZ5PQfn0btMWICaQ": 8,
        "01bWQ4TPGmsP6FS64nF4R9": 6
    },
    "your": {
        "00YeYHw6zhoy1y7EPTgIkj": 9,
        "00Z0GIRi0l7WqQnQJCo5S2": 21,
        "014V6u9VubefjaPPl1QkTJ": 6
    },
    "yourself": {
        "00Z0GIRi0l7WqQnQJCo5S2": 3,
        "014V6u9VubefjaPPl1QkTJ": 2
    },
    "zamorano": {
        "00X2yv2vrtritPt2CZnUTZ": 1
    },
    "zeg": {
        "01bWQ4TPGmsP6FS64nF4R9": 3
    },
    "zie": {
        "01bWQ4TPGmsP6FS64nF4R9": 3
    },
    "zip": {
        "00WIXhVVhswHuS6dlkScuw": 2
    },
    "zone": {
        "014V6u9VubefjaPPl1QkTJ": 1
    },
    "à": {
        "00X2yv2vrtritPt2CZnUTZ": 6
    },
    "ça": {
        "00X2yv2vrtritPt2CZnUTZ": 3
    },
    "écout": {
        "00X2yv2vrtritPt2CZnUTZ": 1
    }
}